MLD/Main.py
MLD/__init__.py
MLDToolkit-0.5.2.dist-info/LICENSE
MLDToolkit-0.5.2.dist-info/METADATA
MLDToolkit-0.5.2.dist-info/WHEEL
MLDToolkit-0.5.2.dist-info/top_level.txt
MLDToolkit-0.5.2.dist-info/RECORD
