Metadata-Version: 2.1
Name: MLDToolkit
Version: 0.5.2
Summary: A text analysis tool.
Home-page: https://github.com/jorymorrison/MLD
Author: Matthew Zorumski
Author-email: mattzor@cox.net
License: Apache License 2.0
Platform: UNKNOWN
Classifier: Programming Language :: Python :: 3
Classifier: License :: OSI Approved :: Apache Software License
Classifier: Operating System :: OS Independent
Requires-Python: >=3.6
